.coveragerc
.editorconfig
.travis.yml
CHANGES.rst
CONTRIBUTORS.rst
LICENSE
MANIFEST.in
README.rst
bootstrap.py
buildout.cfg
setup.py
travis.cfg
buildout.d/base.cfg
buildout.d/checkouts.cfg
buildout.d/development.cfg
buildout.d/jenkins.cfg
buildout.d/sources.cfg
buildout.d/versions.cfg
docs/LICENSE.GPL
docs/LICENSE.rst
src/collective/__init__.py
src/collective/__init__.pyc
src/collective.subsitebehaviors.egg-info/PKG-INFO
src/collective.subsitebehaviors.egg-info/SOURCES.txt
src/collective.subsitebehaviors.egg-info/dependency_links.txt
src/collective.subsitebehaviors.egg-info/entry_points.txt
src/collective.subsitebehaviors.egg-info/namespace_packages.txt
src/collective.subsitebehaviors.egg-info/not-zip-safe
src/collective.subsitebehaviors.egg-info/requires.txt
src/collective.subsitebehaviors.egg-info/top_level.txt
src/collective/subsitebehaviors/__init__.py
src/collective/subsitebehaviors/__init__.pyc
src/collective/subsitebehaviors/behaviors.py
src/collective/subsitebehaviors/behaviors.pyc
src/collective/subsitebehaviors/configure.zcml
src/collective/subsitebehaviors/interfaces.py
src/collective/subsitebehaviors/interfaces.pyc
src/collective/subsitebehaviors/testing.py
src/collective/subsitebehaviors/testing.pyc
src/collective/subsitebehaviors/testing.zcml
src/collective/subsitebehaviors/utils.py
src/collective/subsitebehaviors/utils.pyc
src/collective/subsitebehaviors/browser/__init__.py
src/collective/subsitebehaviors/browser/__init__.pyc
src/collective/subsitebehaviors/browser/configure.zcml
src/collective/subsitebehaviors/browser/cssviewlet.pt
src/collective/subsitebehaviors/browser/cssviewlet.py
src/collective/subsitebehaviors/browser/cssviewlet.pyc
src/collective/subsitebehaviors/browser/subsitelogoviewlet.pt
src/collective/subsitebehaviors/browser/subsitelogoviewlet.py
src/collective/subsitebehaviors/browser/subsitelogoviewlet.pyc
src/collective/subsitebehaviors/browser/overrides/.gitkeep
src/collective/subsitebehaviors/browser/static/.gitkeep
src/collective/subsitebehaviors/locales/collective.subsitebehaviors-manual.pot
src/collective/subsitebehaviors/locales/collective.subsitebehaviors.pot
src/collective/subsitebehaviors/locales/update.sh
src/collective/subsitebehaviors/locales/fi/LC_MESSAGES/collective.subsitebehaviors.mo
src/collective/subsitebehaviors/locales/fi/LC_MESSAGES/collective.subsitebehaviors.po
src/collective/subsitebehaviors/profiles/default/browserlayer.xml
