Metadata-Version: 1.1
Name: collective.subsitebehaviors
Version: 0.4
Summary: Custom logo and css behaviors for subsites
Home-page: http://pypi.python.org/pypi/collective.subsitebehaviors
Author: Petri Savolainen
Author-email: petri.savolainen@koodaamo.fi
License: GPL
Keywords: Plone Python
Platform: UNKNOWN
Classifier: Environment :: Web Environment
Classifier: Framework :: Plone
Classifier: Framework :: Plone :: 4.3
Classifier: Programming Language :: Python
Classifier: Programming Language :: Python :: 2.7
